TechnicalIndicatorsAndOverlays/README.md
TechnicalIndicatorsAndOverlays/__init__.py
TechnicalIndicatorsAndOverlays/__main__.py
TechnicalIndicatorsAndOverlays/file.epub
TechnicalIndicatorsAndOverlays/index.html
TechnicalIndicatorsAndOverlays/css/__init__.py
TechnicalIndicatorsAndOverlays/css/annotations.css
TechnicalIndicatorsAndOverlays/css/main.css
TechnicalIndicatorsAndOverlays/css/normalize.css
TechnicalIndicatorsAndOverlays/css/popup.css
TechnicalIndicatorsAndOverlays/font/__init__.py
TechnicalIndicatorsAndOverlays/font/fontello.eot
TechnicalIndicatorsAndOverlays/font/fontello.svg
TechnicalIndicatorsAndOverlays/font/fontello.ttf
TechnicalIndicatorsAndOverlays/font/fontello.woff
TechnicalIndicatorsAndOverlays/img/__init__.py
TechnicalIndicatorsAndOverlays/img/annotator-glyph-sprite.png
TechnicalIndicatorsAndOverlays/img/annotator-icon-sprite.png
TechnicalIndicatorsAndOverlays/img/apple-touch-icon.png
TechnicalIndicatorsAndOverlays/img/cancelfullscreen.png
TechnicalIndicatorsAndOverlays/img/close.png
TechnicalIndicatorsAndOverlays/img/fullscreen.png
TechnicalIndicatorsAndOverlays/img/loader.gif
TechnicalIndicatorsAndOverlays/img/menu-icon.png
TechnicalIndicatorsAndOverlays/img/save.png
TechnicalIndicatorsAndOverlays/img/saved.png
TechnicalIndicatorsAndOverlays/img/settings-s.png
TechnicalIndicatorsAndOverlays/img/settings.png
TechnicalIndicatorsAndOverlays/img/star.png
TechnicalIndicatorsAndOverlays/js/__init__.py
TechnicalIndicatorsAndOverlays/js/epub.js
TechnicalIndicatorsAndOverlays/js/epub.min.js
TechnicalIndicatorsAndOverlays/js/epub.min.map
TechnicalIndicatorsAndOverlays/js/hooks.min.js
TechnicalIndicatorsAndOverlays/js/hooks.min.map
TechnicalIndicatorsAndOverlays/js/reader.js
TechnicalIndicatorsAndOverlays/js/reader.js.map
TechnicalIndicatorsAndOverlays/js/reader.min.js
TechnicalIndicatorsAndOverlays/js/reader.min.map
TechnicalIndicatorsAndOverlays/js/hooks/__init__.py
TechnicalIndicatorsAndOverlays/js/hooks/extensions/__init__.py
technical_indicators_and_overlays-2024.3.3.0.dist-info/METADATA
technical_indicators_and_overlays-2024.3.3.0.dist-info/WHEEL
technical_indicators_and_overlays-2024.3.3.0.dist-info/entry_points.txt
technical_indicators_and_overlays-2024.3.3.0.dist-info/top_level.txt
technical_indicators_and_overlays-2024.3.3.0.dist-info/RECORD
